selectolax-0.4.6.dist-info/RECORD
selectolax-0.4.6.dist-info/WHEEL
selectolax-0.4.6.dist-info/top_level.txt
selectolax-0.4.6.dist-info/METADATA
selectolax-0.4.6.dist-info/licenses/LICENSE
selectolax/lexbor.pyi
selectolax/parser.pyx
selectolax/parser.cpython-311-darwin.so
selectolax/lexbor.cpython-311-darwin.so
selectolax/__init__.py
selectolax/lexbor.pxd
selectolax/lexbor.pyx
selectolax/parser.pyi
selectolax/utils.pxi
selectolax/lexbor.c
selectolax/py.typed
selectolax/parser.c
selectolax/base.pxi
selectolax/parser.pxd
selectolax/modest/selection.pxi
selectolax/modest/util.pxi
selectolax/modest/node.pxi
selectolax/lexbor/selection.pxi
selectolax/lexbor/util.pxi
selectolax/lexbor/node.pxi
selectolax/lexbor/node_remove.pxi
selectolax/lexbor/attrs.pxi
