Metadata-Version: 2.4
Name: selectolax
Version: 0.4.6
Summary: A fast HTML5 parser with CSS selectors, written in Cython, using Modest and Lexbor engines.
Home-page: https://github.com/rushter/selectolax
Author: Artem Golubin
Author-email: Artem Golubin <me@rushter.com>
License-Expression: MIT
Project-URL: Homepage, https://github.com/rushter/selectolax
Project-URL: Repository, https://github.com/rushter/selectolax
Project-URL: Documentation, https://selectolax.readthedocs.io/en/latest/parser.html
Project-URL: Changelog, https://github.com/rushter/selectolax/blob/master/CHANGES.md
Keywords: selectolax,html,parser,css,fast,lexbor,modest
Classifier: Development Status :: 5 - Production/Stable
Classifier: Environment :: Web Environment
Classifier: Intended Audience :: Developers
Classifier: Natural Language :: English
Classifier: Operating System :: MacOS
Classifier: Operating System :: Microsoft :: Windows
Classifier: Operating System :: OS Independent
Classifier: Operating System :: Unix
Classifier: Programming Language :: Cython
Classifier: Programming Language :: Python
Classifier: Programming Language :: Python :: 3
Classifier: Programming Language :: Python :: 3 :: Only
Classifier: Programming Language :: Python :: 3.9
Classifier: Programming Language :: Python :: 3.10
Classifier: Programming Language :: Python :: 3.11
Classifier: Programming Language :: Python :: 3.12
Classifier: Programming Language :: Python :: 3.13
Classifier: Programming Language :: Python :: 3.14
Classifier: Programming Language :: Python :: Implementation :: CPython
Classifier: Topic :: Internet
Classifier: Topic :: Internet :: WWW/HTTP
Classifier: Topic :: Software Development
Classifier: Topic :: Software Development :: Libraries
Classifier: Topic :: Software Development :: Libraries :: Python Modules
Classifier: Topic :: Text Processing
Classifier: Topic :: Text Processing :: Markup
Classifier: Topic :: Text Processing :: Markup :: HTML
Classifier: Typing :: Typed
Requires-Python: <3.15,>=3.9
License-File: LICENSE
Provides-Extra: cython
Requires-Dist: Cython; extra == "cython"
Dynamic: author
Dynamic: home-page
Dynamic: license-file
